kar/__init__.py
kar/api.py
kar-1.3.5.dist-info/METADATA
kar-1.3.5.dist-info/WHEEL
kar-1.3.5.dist-info/top_level.txt
kar-1.3.5.dist-info/RECORD
