Metadata-Version: 2.1
Name: kar
Version: 1.3.5
Summary: KAR Python SDK.
Home-page: https://github.com/IBM/kar
Author: KAR authors
License: Apache 2.0
Project-URL: Bug Reports, https://github.com/IBM/kar/issues
Project-URL: Source, https://github.com/IBM/kar
Requires-Python: >=3.6
Requires-Dist: hypercorn (>=0.13.2)
Requires-Dist: fastapi (>=0.74.1)
Requires-Dist: httpx (>=0.22.0)
Requires-Dist: httpx[http2]
Requires-Dist: aiohttp (>=3.8.0)
Requires-Dist: asyncio (>=3.4.3)
Requires-Dist: pytest (>=6.2.3)
Requires-Dist: pytest-asyncio
Requires-Dist: requests (>=2.27.1)
